navimysql/__init__.py
navimysql/cli.py
navimysql/plugins/__init__.py
navimysql/plugins/add.py
navimysql/plugins/add_helper.py
navimysql/plugins/agent_export.py
navimysql/plugins/agent_group_export.py
navimysql/plugins/agents.py
navimysql/plugins/agroup.py
navimysql/plugins/api.py
navimysql/plugins/api_wrapper.py
navimysql/plugins/cancel.py
navimysql/plugins/compliance_export_csv.py
navimysql/plugins/consec_export.py
navimysql/plugins/cs.py
navimysql/plugins/database.py
navimysql/plugins/dbconfig.py
navimysql/plugins/delete.py
navimysql/plugins/display.py
navimysql/plugins/error_msg.py
navimysql/plugins/export.py
navimysql/plugins/find.py
navimysql/plugins/http.py
navimysql/plugins/ip.py
navimysql/plugins/keys.py
navimysql/plugins/licensed_count.py
navimysql/plugins/listen.py
navimysql/plugins/lumin.py
navimysql/plugins/lumin_export.py
navimysql/plugins/mac.py
navimysql/plugins/mail.py
navimysql/plugins/migrate.py
navimysql/plugins/network.py
navimysql/plugins/push.py
navimysql/plugins/query_export.py
navimysql/plugins/scan.py
navimysql/plugins/scan_evaluation.py
navimysql/plugins/scanners.py
navimysql/plugins/send_mail.py
navimysql/plugins/smtp.py
navimysql/plugins/ssh.py
navimysql/plugins/tag.py
navimysql/plugins/tag_export.py
navimysql/plugins/tag_helper.py
navimysql/plugins/target_group.py
navimysql/plugins/th_asset_export.py
navimysql/plugins/th_compliance_export.py
navimysql/plugins/th_vuln_export.py
navimysql/plugins/update.py
navimysql/plugins/user.py
navimysql/plugins/user_export.py
navimysql/plugins/usergroup.py
navimysql/plugins/was.py
navimysql/plugins/was_data_export.py
navimysql/plugins/was_detailed_csv.py
navimysql/plugins/was_v2_export.py
navimysql/plugins/web_scan.py
navi_pro_mysql-1.0.1.dist-info/LICENSE
navi_pro_mysql-1.0.1.dist-info/METADATA
navi_pro_mysql-1.0.1.dist-info/WHEEL
navi_pro_mysql-1.0.1.dist-info/entry_points.txt
navi_pro_mysql-1.0.1.dist-info/top_level.txt
navi_pro_mysql-1.0.1.dist-info/RECORD
