Metadata-Version: 2.1
Name: navi-pro-mysql
Version: 1.0.1
Summary: A command-line interface to Tenable.io
Home-page: UNKNOWN
Author: Steve Proud
Author-email: sproud22@gmail.com
License: GNUv3
Keywords: tenable tenable_io navi tio,lumin,navi pro,tio cli,tenable io cli,automation
Platform: UNKNOWN
Classifier: Programming Language :: Python :: 3
Classifier: License :: OSI Approved :: GNU General Public License v3 (GPLv3)
Classifier: Operating System :: OS Independent
Requires-Python: >=3.0
License-File: LICENSE
Requires-Dist: Click (>=7.0)
Requires-Dist: requests
Requires-Dist: flask
Requires-Dist: IPy
Requires-Dist: pytenable (>=1.3)
Requires-Dist: arrow (>=0.17.0)
Requires-Dist: boto3 (>=1.17.48)
Requires-Dist: pexpect (>=4.8.0)
